{
  "metrics": {
    "metrics_val": [
      {
        "ndcg": [
          0.914081743036181,
          0.07145168463574424
        ],
        "precision@05": [
          0.22247191011235956,
          0.19531179854059114
        ],
        "recall@100": [
          1.0,
          0.0
        ],
        "recall@05": [
          0.5712291453864488,
          0.41197119022200046
        ]
      },
      {
        "ndcg": [
          0.9178443505253978,
          0.07206827759027357
        ],
        "precision@05": [
          0.2269662921348315,
          0.1970364963306335
        ],
        "recall@100": [
          1.0,
          0.0
        ],
        "recall@05": [
          0.5858358869594825,
          0.41259549440019266
        ]
      },
      {
        "ndcg": [
          0.9196383862846427,
          0.07366707904269253
        ],
        "precision@05": [
          0.23595505617977527,
          0.19559600132124894
        ],
        "recall@100": [
          1.0,
          0.0
        ],
        "recall@05": [
          0.607184201566224,
          0.40188013990621363
        ]
      },
      {
        "ndcg": [
          0.9213219331266026,
          0.07511548152420669
        ],
        "precision@05": [
          0.23820224719101127,
          0.196317570048014
        ],
        "recall@100": [
          1.0,
          0.0
        ],
        "recall@05": [
          0.610929519918284,
          0.4028507714079802
        ]
      },
      {
        "ndcg": [
          0.9238785915904463,
          0.07503551248162266
        ],
        "precision@05": [
          0.24943820224719104,
          0.2125942463867922
        ],
        "recall@100": [
          1.0,
          0.0
        ],
        "recall@05": [
          0.6300306435137896,
          0.39709713441511446
        ]
      },
      {
        "ndcg": [
          0.9245698459992195,
          0.07578086352265215
        ],
        "precision@05": [
          0.2539325842696629,
          0.21149876073442594
        ],
        "recall@100": [
          1.0,
          0.0
        ],
        "recall@05": [
          0.6412665985699694,
          0.39324019446360875
        ]
      },
      {
        "ndcg": [
          0.9277076194385387,
          0.07474502000719567
        ],
        "precision@05": [
          0.25617977528089886,
          0.21197575448583064
        ],
        "recall@100": [
          1.0,
          0.0
        ],
        "recall@05": [
          0.6506298944501192,
          0.3933366574263027
        ]
      },
      {
        "ndcg": [
          0.9268108000572484,
          0.07485625894797394
        ],
        "precision@05": [
          0.251685393258427,
          0.2131161837218638
        ],
        "recall@100": [
          1.0,
          0.0
        ],
        "recall@05": [
          0.6468845760980593,
          0.39790060490431195
        ]
      },
      {
        "ndcg": [
          0.9291966556529435,
          0.07500024536413086
        ],
        "precision@05": [
          0.25168539325842704,
          0.21311618372186375
        ],
        "recall@100": [
          1.0,
          0.0
        ],
        "recall@05": [
          0.6483827034388832,
          0.39646363932460166
        ]
      },
      {
        "ndcg": [
          0.930063917538722,
          0.07508301166094787
        ],
        "precision@05": [
          0.25842696629213485,
          0.21242790648263327
        ],
        "recall@100": [
          1.0,
          0.0
        ],
        "recall@05": [
          0.6745999319033026,
          0.3888606262751151
        ]
      },
      {
        "ndcg": [
          0.9282132583339108,
          0.07517583073864824
        ],
        "precision@05": [
          0.26067415730337085,
          0.2128553750330718
        ],
        "recall@100": [
          1.0,
          0.0
        ],
        "recall@05": [
          0.6774089206673476,
          0.3866801657240105
        ]
      }
    ],
    "metrics_train": [
      {
        "ndcg": [
          0.9286115578135116,
          0.07419108819216615
        ],
        "precision@05": [
          0.3722955145118734,
          0.273205842653651
        ],
        "recall@100": [
          1.0,
          0.0
        ],
        "recall@05": [
          0.5265251317837725,
          0.36788281577206294
        ]
      },
      {
        "ndcg": [
          0.9304856273800619,
          0.07309440384112208
        ],
        "precision@05": [
          0.37994722955145116,
          0.27531511782287454
        ],
        "recall@100": [
          1.0,
          0.0
        ],
        "recall@05": [
          0.5363116525266142,
          0.36869637325626464
        ]
      },
      {
        "ndcg": [
          0.9323622937489553,
          0.07160843650830077
        ],
        "precision@05": [
          0.3865435356200528,
          0.2760031931274041
        ],
        "recall@100": [
          1.0,
          0.0
        ],
        "recall@05": [
          0.5423227721862671,
          0.364204807751943
        ]
      },
      {
        "ndcg": [
          0.9345798092751494,
          0.07008698328656701
        ],
        "precision@05": [
          0.3949868073878628,
          0.2793248311617274
        ],
        "recall@100": [
          1.0,
          0.0
        ],
        "recall@05": [
          0.5510279979924164,
          0.35999931151123515
        ]
      },
      {
        "ndcg": [
          0.9367517191094769,
          0.06950085557199319
        ],
        "precision@05": [
          0.40052770448548813,
          0.2790858355166444
        ],
        "recall@100": [
          1.0,
          0.0
        ],
        "recall@05": [
          0.5560628110023068,
          0.3581434581731553
        ]
      },
      {
        "ndcg": [
          0.938013140811328,
          0.06864979046682364
        ],
        "precision@05": [
          0.40844327176781003,
          0.2772508343468488
        ],
        "recall@100": [
          1.0,
          0.0
        ],
        "recall@05": [
          0.5647084419764338,
          0.3524379093324503
        ]
      },
      {
        "ndcg": [
          0.9400010916319659,
          0.0674712866180218
        ],
        "precision@05": [
          0.4121372031662269,
          0.2799555602947278
        ],
        "recall@100": [
          1.0,
          0.0
        ],
        "recall@05": [
          0.5682720641746206,
          0.35280720992985887
        ]
      },
      {
        "ndcg": [
          0.9407351275241878,
          0.06694985288492206
        ],
        "precision@05": [
          0.41635883905013193,
          0.2812456986379457
        ],
        "recall@100": [
          1.0,
          0.0
        ],
        "recall@05": [
          0.5703799601372814,
          0.35105846632381676
        ]
      },
      {
        "ndcg": [
          0.9418632066957509,
          0.06722887940551489
        ],
        "precision@05": [
          0.4182058047493404,
          0.2843980819029052
        ],
        "recall@100": [
          1.0,
          0.0
        ],
        "recall@05": [
          0.5736885455970389,
          0.35200140379785766
        ]
      },
      {
        "ndcg": [
          0.9419291557070131,
          0.06724238349841061
        ],
        "precision@05": [
          0.42058047493403705,
          0.2869155056389036
        ],
        "recall@100": [
          1.0,
          0.0
        ],
        "recall@05": [
          0.5742432679195711,
          0.35068443671473665
        ]
      },
      {
        "ndcg": [
          0.9412332464189702,
          0.06758478129181661
        ],
        "precision@05": [
          0.41952506596306066,
          0.2856992279373415
        ],
        "recall@100": [
          1.0,
          0.0
        ],
        "recall@05": [
          0.5745763048621066,
          0.34995782863416525
        ]
      }
    ]
  },
  "test_metrics": {
    "dcg": [
      28.49404520280215,
      14.439557997897545
    ],
    "dcg@03": [
      8.247595782294296,
      2.6726498801128664
    ],
    "dcg@05": [
      10.82272749703865,
      3.0862282109337955
    ],
    "dcg@10": [
      15.479788621422605,
      4.319275578760975
    ],
    "dcg@20": [
      21.030477523961277,
      6.742495931300698
    ],
    "ndcg": [
      0.9365045022187131,
      0.06725935058658611
    ],
    "ndcg@03": [
      0.7990711792193113,
      0.22854929681139513
    ],
    "ndcg@05": [
      0.8284062326685895,
      0.19292988940698994
    ],
    "ndcg@10": [
      0.8682024400764345,
      0.14812257759107764
    ],
    "ndcg@20": [
      0.9010265921357075,
      0.11658250097573439
    ],
    "precision@01": [
      0.43478260869565216,
      0.49572844569527735
    ],
    "precision@03": [
      0.29347826086956524,
      0.2729441879224523
    ],
    "precision@05": [
      0.23695652173913045,
      0.2145355911003376
    ],
    "precision@10": [
      0.17934782608695649,
      0.17101871463715212
    ],
    "precision@20": [
      0.11956521739130437,
      0.1281041784224877
    ],
    "recall@01": [
      0.2913755175983437,
      0.41647993352072454
    ],
    "recall@03": [
      0.48307237750172527,
      0.43676654822860567
    ],
    "recall@05": [
      0.5964095536106406,
      0.41465039576655705
    ],
    "recall@10": [
      0.7500033330196372,
      0.34376049467793596
    ],
    "recall@100": [
      1.0,
      0.0
    ],
    "recall@20": [
      0.8869398566409437,
      0.23768455988456325
    ],
    "relevant rank": [
      14.06159420289855,
      17.469015313097696
    ],
    "relevant rank per query": [
      42.18478260869565,
      81.5941613090995
    ]
  },
  "test_query_level_metrics": {
    "ndcg": [
      0.9918169253863549,
      0.7309951258425472,
      0.885419087963836,
      1.0,
      0.9491448774308947,
      1.0,
      1.0,
      0.9027391661455023,
      1.0,
      0.9125593417913446,
      0.8642612722971558,
      1.0,
      0.7892289082182319,
      1.0,
      0.9010137392502989,
      1.0,
      0.9696134078163657,
      1.0,
      1.0,
      0.834238474284328,
      0.9378242023081572,
      1.0,
      0.9177706625577532,
      1.0,
      1.0,
      0.9837106760320216,
      0.9287748409545289,
      1.0,
      0.8959394632136638,
      1.0,
      0.9113472369574304,
      0.8453639398297458,
      0.9040883422898575,
      0.9436954197559896,
      0.7906412974639916,
      0.9174136592625174,
      1.0,
      0.8906936277777977,
      0.8616746522843942,
      1.0,
      1.0,
      1.0,
      1.0,
      0.9411143516915131,
      0.964791580395086,
      0.885453847261712,
      0.7537634586105365,
      0.8699821192546184,
      0.8656542203865438,
      0.898515269875404,
      1.0,
      1.0,
      1.0,
      0.8785263836104119,
      1.0,
      0.8798668289298159,
      1.0,
      1.0,
      0.8974662480664399,
      1.0,
      0.9702905111559001,
      0.8116280933404912,
      1.0,
      1.0,
      0.842851108396331,
      0.8539075520823908,
      0.9152584423413097,
      0.9609862361233035,
      0.9556261253536436,
      0.8825689090567187,
      0.9078331077296241,
      0.9243690877046408,
      0.8339912323981488,
      0.875691442570683,
      1.0,
      0.8604054909209664,
      1.0,
      0.9365663639217509,
      0.8339912323981488,
      1.0,
      1.0,
      0.9438640649493388,
      0.9003297585930801,
      0.8344245681033876,
      0.8647422923089427,
      1.0,
      1.0,
      1.0,
      1.0,
      1.0,
      0.8999544154010324,
      0.9704862219772203,
      1.0,
      1.0,
      0.8373584420499531,
      1.0,
      1.0,
      0.8470747905759431,
      0.960004383867874,
      1.0,
      0.8728031921662144,
      0.882200452212269,
      0.9555463832582358,
      0.8172938573962647,
      0.8517718783821172,
      0.9788623908788767,
      0.8109181550221998,
      0.9689597704662614,
      0.9579688215370323,
      0.9008481346377668,
      0.9043846167040538,
      0.9925173980023002,
      0.9706160863806146,
      1.0,
      1.0,
      1.0,
      0.9914311879582521,
      0.93210240828806
    ],
    "precision@05": [
      0.2,
      0.0,
      0.2,
      0.2,
      0.2,
      0.2,
      0.2,
      0.0,
      0.2,
      0.2,
      0.2,
      0.2,
      0.2,
      0.2,
      0.2,
      0.2,
      0.2,
      0.2,
      0.2,
      0.2,
      0.6,
      0.2,
      0.2,
      0.0,
      0.0,
      0.2,
      0.2,
      0.6,
      0.2,
      0.0,
      0.2,
      0.0,
      0.2,
      0.4,
      0.2,
      0.0,
      0.2,
      0.0,
      0.2,
      0.0,
      0.2,
      0.2,
      0.0,
      0.4,
      0.0,
      0.2,
      0.6,
      0.2,
      0.2,
      0.0,
      0.2,
      0.2,
      0.0,
      0.2,
      0.2,
      0.2,
      0.2,
      0.0,
      0.2,
      0.2,
      0.2,
      0.2,
      0.2,
      0.2,
      0.2,
      0.0,
      0.2,
      0.2,
      0.2,
      0.2,
      0.2,
      0.4,
      0.2,
      0.0,
      0.2,
      0.2,
      0.2,
      0.2,
      0.0,
      0.2,
      0.2,
      0.2,
      1.0,
      0.4,
      0.4,
      0.6,
      0.8,
      0.4,
      1.0,
      0.8,
      1.0,
      0.6
    ],
    "recall@05": [
      1.0,
      0.0,
      1.0,
      1.0,
      1.0,
      0.25,
      1.0,
      0.0,
      0.25,
      0.5,
      1.0,
      1.0,
      0.5,
      1.0,
      1.0,
      0.5,
      1.0,
      1.0,
      1.0,
      1.0,
      0.75,
      1.0,
      1.0,
      0.0,
      0.0,
      1.0,
      1.0,
      0.75,
      1.0,
      0.0,
      1.0,
      0.0,
      1.0,
      1.0,
      0.5,
      0.0,
      0.25,
      0.0,
      0.3333333333333333,
      0.0,
      0.5,
      1.0,
      0.0,
      1.0,
      0.0,
      1.0,
      1.0,
      0.3333333333333333,
      0.2,
      0.0,
      0.5,
      1.0,
      0.0,
      0.14285714285714285,
      0.3333333333333333,
      1.0,
      1.0,
      0.0,
      1.0,
      1.0,
      1.0,
      1.0,
      1.0,
      1.0,
      1.0,
      0.0,
      0.14285714285714285,
      1.0,
      1.0,
      1.0,
      1.0,
      1.0,
      1.0,
      0.0,
      0.5,
      0.5,
      1.0,
      0.2,
      0.0,
      1.0,
      0.1,
      0.09090909090909091,
      0.3125,
      0.2222222222222222,
      0.2857142857142857,
      0.375,
      0.5714285714285714,
      0.14285714285714285,
      0.8333333333333334,
      0.3333333333333333,
      0.4166666666666667,
      0.25
    ]
  }
}